awake_guardian/__init__.py
awake_guardian/autostart.py
awake_guardian/awake_guardian.py
awake_guardian/config.py
awake_guardian/hold_dialog.py
awake_guardian/lang.py
awake_guardian/power_management.py
awake_guardian/settings_dialog.py
awake_guardian/sounds.py
awake_guardian/system_tray_icon.py
awake_guardian/user_activity.py
awake_guardian/volume_control.py
awake_guardian/audio/coin.mp3
awake_guardian/audio/wilhelm.mp3
awake_guardian/images/beep.png
awake_guardian/images/clock.png
awake_guardian/images/exit.png
awake_guardian/images/eyes.png
awake_guardian/images/inactive.png
awake_guardian/images/settings.png
awake_guardian/images/shout.png
awake_guardian-1.3.1.data/scripts/AwakeGuardian
awake_guardian-1.3.1.dist-info/LICENSE
awake_guardian-1.3.1.dist-info/METADATA
awake_guardian-1.3.1.dist-info/WHEEL
awake_guardian-1.3.1.dist-info/entry_points.txt
awake_guardian-1.3.1.dist-info/top_level.txt
awake_guardian-1.3.1.dist-info/RECORD
