Metadata-Version: 2.1
Name: awake-guardian
Version: 1.3.1
Summary: AwakeGuardia is a program that helps you keep awake and not to fall asleep in front of a computer. The program frequently alerts you when detects your inactivity by reminding or later by nagging you using sound. Moreover to save your money your computer can be suspended or powered off.
Home-page: https://github.com/kamil-cy/awake-guardian
Author: Kamil Cyganowski
Author-email: kamil.cyganowski@gmail.com
Classifier: Programming Language :: Python :: 3
Classifier: License :: OSI Approved :: MIT License
Classifier: Operating System :: POSIX :: Linux
Requires-Python: >=3.6
License-File: LICENSE
Requires-Dist: appdirs
Requires-Dist: pynput
Requires-Dist: PySide6
Requires-Dist: pyyaml
Requires-Dist: playsound
Requires-Dist: pyalsaaudio ; platform_system == "Linux"
Requires-Dist: pycaw ; platform_system == "Windows"
